groundcua/__init__.py
groundcua/version.py
groundcua-0.0.1rc1.dist-info/METADATA
groundcua-0.0.1rc1.dist-info/WHEEL
groundcua-0.0.1rc1.dist-info/top_level.txt
groundcua-0.0.1rc1.dist-info/RECORD
