Metadata-Version: 2.4
Name: groundcua
Version: 0.0.1rc1
Summary: Helper utilities and constants for GroundNext models - Computer Use Agents for grounding tasks
Author-email: GroundCUA Team <groundcua@googlegroups.com>
Maintainer-email: GroundCUA Team <groundcua@googlegroups.com>
License: Apache-2.0
Project-URL: Homepage, https://github.com/xhluca/GroundCUA
Project-URL: Repository, https://github.com/xhluca/GroundCUA
Project-URL: Issues, https://github.com/xhluca/GroundCUA/issues
Keywords: computer-use,vision-language-models,grounding,multimodal,qwen,groundnext
Classifier: Development Status :: 3 - Alpha
Classifier: Intended Audience :: Developers
Classifier: Intended Audience :: Science/Research
Classifier: License :: OSI Approved :: Apache Software License
Classifier: Operating System :: OS Independent
Classifier: Programming Language :: Python :: 3
Classifier: Programming Language :: Python :: 3.8
Classifier: Programming Language :: Python :: 3.9
Classifier: Programming Language :: Python :: 3.10
Classifier: Programming Language :: Python :: 3.11
Classifier: Programming Language :: Python :: 3.12
Classifier: Topic :: Scientific/Engineering :: Artificial Intelligence
Classifier: Topic :: Software Development :: Libraries :: Python Modules
Requires-Python: >=3.8
Requires-Dist: transformers>=4.37.0
Requires-Dist: accelerate>=0.27.0
Requires-Dist: qwen-vl-utils>=0.0.1
Requires-Dist: pillow<12.0,>=8.0
Provides-Extra: training
Requires-Dist: peft>=0.8.0; extra == "training"
Requires-Dist: datasets>=2.16.0; extra == "training"
Requires-Dist: deepspeed>=0.12.0; extra == "training"
Requires-Dist: wandb>=0.16.0; extra == "training"
Requires-Dist: tensorboard>=2.15.0; extra == "training"
Requires-Dist: bitsandbytes>=0.41.0; extra == "training"
Provides-Extra: eval
Requires-Dist: numpy>=1.24.0; extra == "eval"
Requires-Dist: pandas>=2.0.0; extra == "eval"
Requires-Dist: scikit-learn>=1.3.0; extra == "eval"
Requires-Dist: matplotlib>=3.7.0; extra == "eval"
Requires-Dist: seaborn>=0.12.0; extra == "eval"
Requires-Dist: tqdm>=4.65.0; extra == "eval"
Provides-Extra: data
Requires-Dist: jsonlines>=4.0.0; extra == "data"
Requires-Dist: pyarrow>=14.0.0; extra == "data"
Requires-Dist: scipy>=1.11.0; extra == "data"
Provides-Extra: dev
Requires-Dist: pytest>=7.0.0; extra == "dev"
Requires-Dist: black>=23.0.0; extra == "dev"
Requires-Dist: isort>=5.12.0; extra == "dev"
Requires-Dist: flake8>=6.0.0; extra == "dev"
Provides-Extra: all
Requires-Dist: groundcua[data,dev,eval,training]; extra == "all"
